[
  {
    "MarcaSella": "Cavallino",
    "Targa": "",
    "Marca": "DUCATI",
    "Modello": "Squalo",
    "Colore": "Nero",
    "Cilindrata": 1000.0,
    "PotenzaKw": 75.2,
    "Immatricolazione": "2020-04-20T23:35:28.7057604+02:00",
    "IsUsato": false,
    "IsKmZero": false,
    "KmPercorsi": 0.0,
    "Prezzo": 12358.0,
    "ImgPath": ".\\img/noPhoto.jpg"
  },
  {
    "MarcaSella": "Quintino",
    "Targa": "",
    "Marca": "HONDA",
    "Modello": "Tsunami",
    "Colore": "Rosso",
    "Cilindrata": 1000.0,
    "PotenzaKw": 120.0,
    "Immatricolazione": "2020-04-30T23:35:28.7107572+02:00",
    "IsUsato": false,
    "IsKmZero": false,
    "KmPercorsi": 0.0,
    "Prezzo": 12358.0,
    "ImgPath": ".\\img/genericMoto.jpg"
  },
  {
    "NumAirbag": 8,
    "Targa": "",
    "Marca": "JEEP",
    "Modello": "Compass",
    "Colore": "Blue",
    "Cilindrata": 1600.0,
    "PotenzaKw": 90.0,
    "Immatricolazione": "2020-04-23T23:35:28.7107572+02:00",
    "IsUsato": false,
    "IsKmZero": false,
    "KmPercorsi": 0.0,
    "Prezzo": 1235489.0,
    "ImgPath": ".\\img/genericAuto.jpg"
  }
]